plover_xtest_input/__init__.py
plover_xtest_input-0.0.1.dist-info/LICENSE
plover_xtest_input-0.0.1.dist-info/METADATA
plover_xtest_input-0.0.1.dist-info/WHEEL
plover_xtest_input-0.0.1.dist-info/entry_points.txt
plover_xtest_input-0.0.1.dist-info/top_level.txt
plover_xtest_input-0.0.1.dist-info/zip-safe
plover_xtest_input-0.0.1.dist-info/RECORD
